fcmnotify/__init__.py
fcmnotify/admin.py
fcmnotify/apps.py
fcmnotify/sender.py
fcmnotify/urls.py
fcmnotify/forms/__init__.py
fcmnotify/migrations/0001_initial.py
fcmnotify/migrations/__init__.py
fcmnotify/models/__init__.py
fcmnotify/models/fcm_settings.py
fcmnotify/models/user_fcm_token.py
fcmnotify/templates/main.html
fcmnotify/tests/__init__.py
fcmnotify/views/__init__.py
fcmnotify/views/download_fcm_file.py
fcmnotify/views/fcm_controller.py
fcmnotify-1.2.2.dist-info/LICENSE
fcmnotify-1.2.2.dist-info/METADATA
fcmnotify-1.2.2.dist-info/WHEEL
fcmnotify-1.2.2.dist-info/top_level.txt
fcmnotify-1.2.2.dist-info/RECORD
