Metadata-Version: 2.1
Name: fcmnotify
Version: 1.2.2
Summary: A simple Django app to send notifications using Firebase! Adding Firebase Cloud Messaging Service into a Django Project The aim of this repository is to provide a step-by-step guide and a basic project sample to implement FCM (Firebase Cloud Messaging) feature into a django-based project.
Home-page: https://github.com/dkkundu/fcmnotify
Author: Dipto Kumar Kundu
Author-email: dkkundu00@gmail.com
License: MIT License
Classifier: Environment :: Web Environment
Classifier: Framework :: Django
Classifier: Intended Audience :: Developers
Classifier: License :: OSI Approved :: MIT License
Classifier: Operating System :: OS Independent
Classifier: Programming Language :: Python
Classifier: Programming Language :: Python :: 3
Classifier: Programming Language :: Python :: 3.4
Classifier: Programming Language :: Python :: 3.5
Classifier: Programming Language :: Python :: 3.6
Classifier: Programming Language :: Python :: 3.7
Classifier: Programming Language :: Python :: 3.8
Classifier: Programming Language :: Python :: 3.9
Classifier: Programming Language :: Python :: 3.10
Classifier: Topic :: Internet :: WWW/HTTP
Classifier: Topic :: Internet :: WWW/HTTP :: Dynamic Content
License-File: LICENSE
Requires-Dist: requests
